{
  "slots": [
    {
      "id": 1,
      "x1": 8,
      "y1": 35,
      "x2": 111,
      "y2": 268
    },
    {
      "id": 2,
      "x1": 124,
      "y1": 38,
      "x2": 231,
      "y2": 267
    },
    {
      "id": 3,
      "x1": 239,
      "y1": 36,
      "x2": 345,
      "y2": 269
    },
    {
      "id": 4,
      "x1": 350,
      "y1": 37,
      "x2": 465,
      "y2": 266
    },
    {
      "id": 5,
      "x1": 466,
      "y1": 38,
      "x2": 576,
      "y2": 266
    },
    {
      "id": 6,
      "x1": 579,
      "y1": 37,
      "x2": 693,
      "y2": 267
    },
    {
      "id": 7,
      "x1": 695,
      "y1": 37,
      "x2": 810,
      "y2": 266
    },
    {
      "id": 8,
      "x1": 811,
      "y1": 36,
      "x2": 925,
      "y2": 266
    },
    {
      "id": 9,
      "x1": 927,
      "y1": 36,
      "x2": 1041,
      "y2": 267
    },
    {
      "id": 10,
      "x1": 1042,
      "y1": 37,
      "x2": 1156,
      "y2": 266
    },
    {
      "id": 11,
      "x1": 1153,
      "y1": 34,
      "x2": 1272,
      "y2": 265
    },
    {
      "id": 12,
      "x1": 1269,
      "y1": 34,
      "x2": 1386,
      "y2": 267
    },
    {
      "id": 13,
      "x1": 1385,
      "y1": 34,
      "x2": 1501,
      "y2": 266
    },
    {
      "id": 14,
      "x1": 1504,
      "y1": 35,
      "x2": 1624,
      "y2": 264
    },
    {
      "id": 15,
      "x1": 1629,
      "y1": 267,
      "x2": 1870,
      "y2": 375
    },
    {
      "id": 16,
      "x1": 1630,
      "y1": 375,
      "x2": 1870,
      "y2": 483
    },
    {
      "id": 17,
      "x1": 1631,
      "y1": 481,
      "x2": 1870,
      "y2": 590
    },
    {
      "id": 18,
      "x1": 1631,
      "y1": 589,
      "x2": 1870,
      "y2": 699
    },
    {
      "id": 19,
      "x1": 1633,
      "y1": 697,
      "x2": 1870,
      "y2": 808
    },
    {
      "id": 20,
      "x1": 1636,
      "y1": 808,
      "x2": 1870,
      "y2": 919
    },
    {
      "id": 21,
      "x1": 1635,
      "y1": 919,
      "x2": 1870,
      "y2": 1030
    },
    {
      "id": 22,
      "x1": 1077,
      "y1": 593,
      "x2": 1195,
      "y2": 833
    },
    {
      "id": 23,
      "x1": 956,
      "y1": 593,
      "x2": 1076,
      "y2": 834
    },
    {
      "id": 24,
      "x1": 838,
      "y1": 593,
      "x2": 960,
      "y2": 834
    },
    {
      "id": 25,
      "x1": 720,
      "y1": 596,
      "x2": 841,
      "y2": 831
    },
    {
      "id": 26,
      "x1": 606,
      "y1": 594,
      "x2": 721,
      "y2": 837
    },
    {
      "id": 27,
      "x1": 481,
      "y1": 593,
      "x2": 608,
      "y2": 834
    },
    {
      "id": 28,
      "x1": 368,
      "y1": 590,
      "x2": 488,
      "y2": 834
    },
    {
      "id": 29,
      "x1": 247,
      "y1": 594,
      "x2": 371,
      "y2": 837
    },
    {
      "id": 30,
      "x1": 130,
      "y1": 594,
      "x2": 257,
      "y2": 835
    },
    {
      "id": 31,
      "x1": 10,
      "y1": 596,
      "x2": 142,
      "y2": 836
    },
    {
      "id": 32,
      "x1": 1071,
      "y1": 833,
      "x2": 1193,
      "y2": 1080
    },
    {
      "id": 33,
      "x1": 952,
      "y1": 836,
      "x2": 1073,
      "y2": 1078
    },
    {
      "id": 34,
      "x1": 833,
      "y1": 833,
      "x2": 955,
      "y2": 1078
    },
    {
      "id": 35,
      "x1": 720,
      "y1": 837,
      "x2": 834,
      "y2": 1073
    },
    {
      "id": 36,
      "x1": 600,
      "y1": 834,
      "x2": 715,
      "y2": 1077
    },
    {
      "id": 37,
      "x1": 480,
      "y1": 834,
      "x2": 598,
      "y2": 1080
    },
    {
      "id": 38,
      "x1": 361,
      "y1": 835,
      "x2": 473,
      "y2": 1077
    },
    {
      "id": 39,
      "x1": 244,
      "y1": 835,
      "x2": 356,
      "y2": 1075
    },
    {
      "id": 40,
      "x1": 121,
      "y1": 836,
      "x2": 238,
      "y2": 1078
    },
    {
      "id": 41,
      "x1": 5,
      "y1": 838,
      "x2": 117,
      "y2": 1081
    }
  ]
}

